sadl/__init__.py
sadl/scripts.py
south_africa_driving_license-0.1.1.dist-info/LICENSE
south_africa_driving_license-0.1.1.dist-info/METADATA
south_africa_driving_license-0.1.1.dist-info/WHEEL
south_africa_driving_license-0.1.1.dist-info/entry_points.txt
south_africa_driving_license-0.1.1.dist-info/top_level.txt
south_africa_driving_license-0.1.1.dist-info/RECORD
